mcp_google_ads/__init__.py
mcp_google_ads/py.typed
mcp_google_ads/server.py
mcp_google_ads-0.2.6.dist-info/licenses/LICENSE
mcp_google_ads-0.2.6.dist-info/METADATA
mcp_google_ads-0.2.6.dist-info/WHEEL
mcp_google_ads-0.2.6.dist-info/entry_points.txt
mcp_google_ads-0.2.6.dist-info/top_level.txt
mcp_google_ads-0.2.6.dist-info/RECORD
