Metadata-Version: 2.4
Name: mcp-google-ads
Version: 0.2.6
Summary: Google Ads API integration for Model Context Protocol (MCP) with full campaign management capabilities
Author-email: Ernesto Cohnen <ernesto@ixigo.com>
License-Expression: MIT
Project-URL: Homepage, https://github.com/cohnen/mcp-google-ads
Project-URL: Bug Tracker, https://github.com/cohnen/mcp-google-ads/issues
Keywords: mcp,google ads,seo,sem,claude,search analytics,campaign management,automation
Classifier: Development Status :: 4 - Beta
Classifier: Intended Audience :: Developers
Classifier: Programming Language :: Python :: 3
Classifier: Programming Language :: Python :: 3.11
Classifier: Topic :: Internet :: WWW/HTTP :: Indexing/Search
Classifier: Topic :: Software Development :: Libraries :: Python Modules
Requires-Python: >=3.11
License-File: LICENSE
Requires-Dist: google-api-python-client>=2.163.0
Requires-Dist: google-auth-httplib2>=0.2.0
Requires-Dist: google-auth-oauthlib>=1.2.1
Requires-Dist: google-auth>=2.25.2
Requires-Dist: mcp[cli]>=1.3.0
Requires-Dist: requests>=2.25.0
Requires-Dist: python-dotenv>=0.19.0
Provides-Extra: image
Requires-Dist: Pillow>=10.0.0; extra == "image"
Provides-Extra: visualization
Requires-Dist: matplotlib>=3.7.3; extra == "visualization"
Requires-Dist: pandas>=2.1.4; extra == "visualization"
Provides-Extra: dev
Requires-Dist: pytest>=7.0.0; extra == "dev"
Requires-Dist: black>=22.0.0; extra == "dev"
Requires-Dist: mypy>=0.950; extra == "dev"
Dynamic: license-file
